mylib_042/__init__.py
mylib_042-0.1.dist-info/LICENSE.txt
mylib_042-0.1.dist-info/METADATA
mylib_042-0.1.dist-info/WHEEL
mylib_042-0.1.dist-info/top_level.txt
mylib_042-0.1.dist-info/RECORD
